PaddlepaddleShenduXuexiRumen/README.md
PaddlepaddleShenduXuexiRumen/__init__.py
PaddlepaddleShenduXuexiRumen/__main__.py
PaddlepaddleShenduXuexiRumen/file.epub
PaddlepaddleShenduXuexiRumen/index.html
PaddlepaddleShenduXuexiRumen/css/__init__.py
PaddlepaddleShenduXuexiRumen/css/annotations.css
PaddlepaddleShenduXuexiRumen/css/main.css
PaddlepaddleShenduXuexiRumen/css/normalize.css
PaddlepaddleShenduXuexiRumen/css/popup.css
PaddlepaddleShenduXuexiRumen/font/__init__.py
PaddlepaddleShenduXuexiRumen/font/fontello.eot
PaddlepaddleShenduXuexiRumen/font/fontello.svg
PaddlepaddleShenduXuexiRumen/font/fontello.ttf
PaddlepaddleShenduXuexiRumen/font/fontello.woff
PaddlepaddleShenduXuexiRumen/img/__init__.py
PaddlepaddleShenduXuexiRumen/img/annotator-glyph-sprite.png
PaddlepaddleShenduXuexiRumen/img/annotator-icon-sprite.png
PaddlepaddleShenduXuexiRumen/img/apple-touch-icon.png
PaddlepaddleShenduXuexiRumen/img/cancelfullscreen.png
PaddlepaddleShenduXuexiRumen/img/close.png
PaddlepaddleShenduXuexiRumen/img/fullscreen.png
PaddlepaddleShenduXuexiRumen/img/loader.gif
PaddlepaddleShenduXuexiRumen/img/menu-icon.png
PaddlepaddleShenduXuexiRumen/img/save.png
PaddlepaddleShenduXuexiRumen/img/saved.png
PaddlepaddleShenduXuexiRumen/img/settings-s.png
PaddlepaddleShenduXuexiRumen/img/settings.png
PaddlepaddleShenduXuexiRumen/img/star.png
PaddlepaddleShenduXuexiRumen/js/__init__.py
PaddlepaddleShenduXuexiRumen/js/epub.js
PaddlepaddleShenduXuexiRumen/js/epub.min.js
PaddlepaddleShenduXuexiRumen/js/epub.min.map
PaddlepaddleShenduXuexiRumen/js/hooks.min.js
PaddlepaddleShenduXuexiRumen/js/hooks.min.map
PaddlepaddleShenduXuexiRumen/js/reader.js
PaddlepaddleShenduXuexiRumen/js/reader.js.map
PaddlepaddleShenduXuexiRumen/js/reader.min.js
PaddlepaddleShenduXuexiRumen/js/reader.min.map
PaddlepaddleShenduXuexiRumen/js/hooks/__init__.py
PaddlepaddleShenduXuexiRumen/js/hooks/extensions/__init__.py
PaddlepaddleShenduXuexiRumen/js/hooks/extensions/highlight.js
paddlepaddle_shendu_xuexi_rumen-2024.3.3.0.dist-info/METADATA
paddlepaddle_shendu_xuexi_rumen-2024.3.3.0.dist-info/WHEEL
paddlepaddle_shendu_xuexi_rumen-2024.3.3.0.dist-info/entry_points.txt
paddlepaddle_shendu_xuexi_rumen-2024.3.3.0.dist-info/top_level.txt
paddlepaddle_shendu_xuexi_rumen-2024.3.3.0.dist-info/RECORD
